docs/source/conf.py
toad/__init__.py
toad/c_utils.c
toad/c_utils.cpython-313-darwin.so
toad/c_utils.pyx
toad/cli.py
toad/cli_test.py
toad/detector.py
toad/impute.py
toad/impute_test.py
toad/merge.c
toad/merge.cpython-313-darwin.so
toad/merge.pyx
toad/merge_test.py
toad/metrics.py
toad/metrics_test.py
toad/plot.py
toad/plot_test.py
toad/scorecard.py
toad/scorecard_test.py
toad/selection.py
toad/selection_test.py
toad/stats.py
toad/stats_test.py
toad/transform.py
toad/transform_test.py
toad/version.py
toad/commands/__init__.py
toad/commands/detect/__init__.py
toad/commands/evaluate/__init__.py
toad/commands/evaluate/evaluate.py
toad/commands/tree/__init__.py
toad/commands/tree/tree.py
toad/nn/__init__.py
toad/nn/functional.py
toad/nn/functional_test.py
toad/nn/loss.py
toad/nn/loss_test.py
toad/nn/module.py
toad/nn/module_test.py
toad/nn/trainer/__init__.py
toad/nn/trainer/callback.py
toad/nn/trainer/callback_test.py
toad/nn/trainer/earlystop.py
toad/nn/trainer/earlystop_test.py
toad/nn/trainer/event.py
toad/nn/trainer/event_test.py
toad/nn/trainer/history.py
toad/nn/trainer/history_test.py
toad/nn/trainer/metrics.py
toad/nn/trainer/trainer.py
toad/nn/trainer/trainer_test.py
toad/nn/zoo/__init__.py
toad/nn/zoo/autoencoder.py
toad/nn/zoo/autoencoder_test.py
toad/preprocessing/__init__.py
toad/preprocessing/partition.py
toad/preprocessing/partition_test.py
toad/preprocessing/process.py
toad/preprocessing/process_test.py
toad/tadpole/__init__.py
toad/tadpole/base.py
toad/tadpole/func.py
toad/tadpole/utils.py
toad/tadpole/fonts/NotoSansCJKsc-Regular.otf
toad/utils/__init__.py
toad/utils/decorator.py
toad/utils/decorator_test.py
toad/utils/func.py
toad/utils/func_test.py
toad/utils/mixin.py
toad/utils/mixin_test.py
toad/utils/pickletracer.py
toad/utils/pickletracer_test.py
toad/utils/progress/__init__.py
toad/utils/progress/pandas.py
toad/utils/progress/pandas_test.py
toad/utils/progress/progress.py
toad/utils/progress/progress_test.py
toad-0.1.5.dist-info/LICENSE
toad-0.1.5.dist-info/METADATA
toad-0.1.5.dist-info/WHEEL
toad-0.1.5.dist-info/top_level.txt
toad-0.1.5.dist-info/RECORD
