Metadata-Version: 2.2
Name: toad
Version: 0.1.5
Summary: Toad is dedicated to facilitating model development process, especially for a scorecard.
Home-page: https://github.com/amphibian-dev/toad
Author: ESC Team
Author-email: Secbone <secbone@gmail.com>
License: MIT License
Project-URL: Homepage, https://github.com/amphibian-dev/toad
Project-URL: Documentation, https://toad.readthedocs.io/en/stable/
Project-URL: Repository, https://github.com/amphibian-dev/toad.git
Project-URL: Issues, https://github.com/amphibian-dev/toad/issues
Project-URL: Changelog, https://github.com/amphibian-dev/toad/blob/master/CHANGELOG.md
Classifier: Operating System :: POSIX
Classifier: Operating System :: Microsoft :: Windows
Classifier: Operating System :: MacOS :: MacOS X
Classifier: Programming Language :: Python :: 3.9
Classifier: Programming Language :: Python :: 3.10
Classifier: Programming Language :: Python :: 3.11
Classifier: Programming Language :: Python :: 3.12
Requires-Python: >=3.7
License-File: LICENSE
Requires-Dist: Cython<=0.29.15; python_version < "3.10"
Requires-Dist: Cython>=0.29.15; python_version >= "3.10"
Requires-Dist: numpy<=1.24; python_version < "3.10"
Requires-Dist: numpy>=1.24; python_version >= "3.10"
Requires-Dist: pandas>=1.5
Requires-Dist: scipy
Requires-Dist: joblib>=0.12
Requires-Dist: scikit-learn>=0.21
Requires-Dist: seaborn>=0.10.0
Requires-Dist: setuptools
Provides-Extra: nn
Requires-Dist: torch>=1.8.1; extra == "nn"
Requires-Dist: torchvision>=0.9.1; extra == "nn"
Requires-Dist: numpy<2.0; sys_platform == "darwin" and extra == "nn"
Provides-Extra: tools
Requires-Dist: cloudpickle; extra == "tools"
Provides-Extra: all
Requires-Dist: torch>=1.8.1; extra == "all"
Requires-Dist: torchvision>=0.9.1; extra == "all"
Requires-Dist: numpy<2.0; sys_platform == "darwin" and extra == "all"
Requires-Dist: cloudpickle; extra == "all"
Dynamic: author
Dynamic: home-page
Dynamic: requires-python
